cubicweb_fluid_design_system/__init__.py
cubicweb_fluid_design_system/__pkginfo__.py
cubicweb_fluid_design_system/site_cubicweb.py
cubicweb_fluid_design_system/uiprops.py
cubicweb_fluid_design_system/data/ajax-loader.gif
cubicweb_fluid_design_system/data/cubes.bootstrap.css
cubicweb_fluid_design_system/data/cubes.bootstrap.cw_compat.css
cubicweb_fluid_design_system/data/cubes.bootstrap.edition.js
cubicweb_fluid_design_system/data/cubes.bootstrap.js
cubicweb_fluid_design_system/data/cubes.squareui.js
cubicweb_fluid_design_system/data/cubicweb.form.css
cubicweb_fluid_design_system/data/cubicweb.tableview.css
cubicweb_fluid_design_system/data/go_next.png
cubicweb_fluid_design_system/data/go_prev.png
cubicweb_fluid_design_system/data/logo-cubicweb.svg
cubicweb_fluid_design_system/data/pen_icon.png
cubicweb_fluid_design_system/data/required.png
cubicweb_fluid_design_system/data/css/bootstrap-theme.css
cubicweb_fluid_design_system/data/css/bootstrap-theme.min.css
cubicweb_fluid_design_system/data/css/bootstrap.min.css
cubicweb_fluid_design_system/data/css/fix.css
cubicweb_fluid_design_system/data/css/fluid-design-system.css
cubicweb_fluid_design_system/data/css/reboot.css
cubicweb_fluid_design_system/data/css/components/alert/index.css
cubicweb_fluid_design_system/data/css/components/alert/index.d.ts
cubicweb_fluid_design_system/data/css/components/alert/index.js
cubicweb_fluid_design_system/data/css/components/avatar/index.css
cubicweb_fluid_design_system/data/css/components/badge/index.css
cubicweb_fluid_design_system/data/css/components/breadcrumb/index.css
cubicweb_fluid_design_system/data/css/components/button/index.css
cubicweb_fluid_design_system/data/css/components/card/index.css
cubicweb_fluid_design_system/data/css/components/checkbox/index.css
cubicweb_fluid_design_system/data/css/components/checkbox/index.d.ts
cubicweb_fluid_design_system/data/css/components/checkbox/index.js
cubicweb_fluid_design_system/data/css/components/collapse/index.css
cubicweb_fluid_design_system-1.10.1.dist-info/METADATA
cubicweb_fluid_design_system-1.10.1.dist-info/WHEEL
cubicweb_fluid_design_system-1.10.1.dist-info/entry_points.txt
cubicweb_fluid_design_system-1.10.1.dist-info/top_level.txt
cubicweb_fluid_design_system-1.10.1.dist-info/RECORD
