Metadata-Version: 2.1
Name: cubicweb-fluid-design-system
Version: 1.10.1
Home-page: 
Author: LOGILAB S.A. (Paris, FRANCE)
Author-email: contact@logilab.fr
License: LGPL
Classifier: Environment :: Web Environment
Classifier: Framework :: CubicWeb
Classifier: Programming Language :: Python
Classifier: Programming Language :: Python :: 3
Classifier: Programming Language :: JavaScript
Requires-Python: >=3.7
Requires-Dist: cubicweb (<3.39.0,>=3.38.0)
